{
    "caption": "Upload",
    "fields": {
        "AAZ": {
            "caption": "type",
            "editor": "DynamicValue",
            "name": "type",
            "optional": true,
            "rank": 0,
            "value": "text"
        },
        "AAa": {
            "caption": "size",
            "editor": "DynamicValue",
            "name": "size",
            "rank": 1,
            "value": "number"
        },
        "AAb": {
            "caption": "max",
            "editor": "DynamicValue",
            "name": "max",
            "rank": 2,
            "value": "number"
        },
        "ABW": {
            "caption": "accesskeyid",
            "editor": "DynamicValue",
            "name": "accesskeyid",
            "rank": 3,
            "value": "text"
        },
        "ABX": {
            "caption": "secretaccesskey",
            "editor": "DynamicValue",
            "name": "secretaccesskey",
            "rank": 4,
            "value": "text"
        },
        "ABY": {
            "caption": "sessiontoken",
            "editor": "DynamicValue",
            "name": "sessiontoken",
            "rank": 5,
            "value": "text"
        },
        "ABZ": {
            "caption": "userid",
            "editor": "DynamicValue",
            "name": "userid",
            "rank": 6,
            "value": "text"
        },
        "ABa": {
            "caption": "timestamp",
            "editor": "DynamicValue",
            "name": "timestamp",
            "rank": 7,
            "value": "number"
        },
        "ABb": {
            "caption": "bucketname",
            "editor": "DynamicValue",
            "name": "bucketname",
            "rank": 8,
            "value": "text"
        }
    }
}